hardware/verilog/core/riscv_core.v
`timescale 1ns / 1ps

module riscv_core (
    input wire clk,
    input wire rst_n,
    output reg [31:0] instr_addr,
    input wire [31:0] instr_data,
    output reg [31:0] data_addr,
    output reg [31:0] data_wdata,
    input wire [31:0] data_rdata,
    output reg data_we,
    output reg data_re,
    output wire [31:0] pc_debug
);
    reg [31:0] pc;
    assign pc_debug = pc;
    
    wire [6:0] opcode = instr_data[6:0];
    wire [4:0] rd = instr_data[11:7];
    wire [2:0] funct3 = instr_data[14:12];
    wire [4:0] rs1 = instr_data[19:15];
    wire [4:0] rs2 = instr_data[24:20];
    wire [6:0] funct7 = instr_data[31:25];
    
    wire [31:0] imm_i = {{20{instr_data[31]}}, instr_data[31:20]};
    wire [31:0] imm_u = {instr_data[31:12], 12'b0};
    
    reg [31:0] regs [0:31];
    wire [31:0] rs1_data = (rs1 == 0) ? 32'd0 : regs[rs1];
    wire [31:0] rs2_data = (rs2 == 0) ? 32'd0 : regs[rs2];
    
    reg [31:0] alu_a, alu_b;
    reg [3:0] alu_op;
    wire [31:0] alu_result;
    
    localparam ALU_ADD = 4'd0;
    localparam ALU_SUB = 4'd1;
    localparam ALU_AND = 4'd2;
    localparam ALU_OR = 4'd3;
    localparam ALU_XOR = 4'd4;
    
    assign alu_result = (alu_op == ALU_ADD) ? (alu_a + alu_b) :
                        (alu_op == ALU_SUB) ? (alu_a - alu_b) :
                        (alu_op == ALU_AND) ? (alu_a & alu_b) :
                        (alu_op == ALU_OR) ? (alu_a | alu_b) :
                        (alu_op == ALU_XOR) ? (alu_a ^ alu_b) : 32'd0;
    
    wire is_op_imm = (opcode == 7'b0010011);
    wire is_op = (opcode == 7'b0110011);
    wire is_lui = (opcode == 7'b0110111);
    
    wire reg_write = is_op_imm || is_op || is_lui;
    wire use_imm = is_op_imm || is_lui;
    
    always @(*) begin
        if (is_op_imm || is_op) begin
            case (funct3)
                3'b000: alu_op = (is_op && funct7[5]) ? ALU_SUB : ALU_ADD;
                3'b111: alu_op = ALU_AND;
                3'b110: alu_op = ALU_OR;
                3'b100: alu_op = ALU_XOR;
                default: alu_op = ALU_ADD;
            endcase
        end else begin
            alu_op = ALU_ADD;
        end
    end
    
    always @(*) begin
        if (is_lui) begin
            alu_a = 32'd0;
            alu_b = imm_u;
        end else if (is_op_imm) begin
            alu_a = rs1_data;
            alu_b = imm_i;
        end else begin
            alu_a = rs1_data;
            alu_b = rs2_data;
        end
    end
    
    always @(*) begin
        data_addr = alu_result;
        data_wdata = rs2_data;
        data_we = 1'b0;
        data_re = 1'b0;
    end
    
    wire [31:0] write_data = is_lui ? imm_u : alu_result;
    
    integer i;
    always @(posedge clk or negedge rst_n) begin
        if (!rst_n) begin
            pc <= 32'h80000000;
            for (i = 0; i < 32; i = i + 1)
                regs[i] <= 32'd0;
        end else begin
            pc <= pc + 4;
            if (reg_write && rd != 0) begin
                regs[rd] <= write_data;
            end
        end
    end
    
    always @(*) begin
        instr_addr = pc;
    end
endmodule

hardware/verilog/testbench/tb_core.v
`timescale 1ns / 1ps

module tb_core;
    reg clk;
    reg rst_n;
    
    wire [31:0] instr_addr;
    reg [31:0] instr_data;
    wire [31:0] data_addr;
    wire [31:0] data_wdata;
    reg [31:0] data_rdata;
    wire data_we;
    wire data_re;
    wire [31:0] pc_debug;
    
    riscv_core uut (
        .clk(clk),
        .rst_n(rst_n),
        .instr_addr(instr_addr),
        .instr_data(instr_data),
        .data_addr(data_addr),
        .data_wdata(data_wdata),
        .data_rdata(data_rdata),
        .data_we(data_we),
        .data_re(data_re),
        .pc_debug(pc_debug)
    );
    
    initial begin
        clk = 0;
        forever #5 clk = ~clk;
    end
    
    initial begin
        rst_n = 0;
        #20 rst_n = 1;
        
        // Test: addi x1, x0, 5
        @(posedge clk);
        instr_data = 32'h00500093;
        
        // Test: addi x2, x1, 3
        @(posedge clk);
        instr_data = 32'h00308113;
        
        // Test: add x3, x1, x2
        @(posedge clk);
        instr_data = 32'h002081b3;
        
        #100;
        $display("Simulation completed");
        $display("PC = 0x%h", pc_debug);
        $finish;
    end
    
    initial begin
        $dumpfile("waveform.vcd");
        $dumpvars(0, tb_core);
    end
endmodule

hardware/verilog/waveform.vcd
$date
	Tue Feb  3 22:59:32 2026
$end
$version
	Icarus Verilog
$end
$timescale
	1ps
$end
$scope module tb_core $end
$var wire 32 ! pc_debug [31:0] $end
$var wire 32 " instr_addr [31:0] $end
$var wire 1 # data_we $end
$var wire 32 $ data_wdata [31:0] $end
$var wire 1 % data_re $end
$var wire 32 & data_addr [31:0] $end
$var reg 1 ' clk $end
$var reg 32 ( data_rdata [31:0] $end
$var reg 32 ) instr_data [31:0] $end
$var reg 1 * rst_n $end
$scope module uut $end
$var wire 1 ' clk $end
$var wire 32 + data_rdata [31:0] $end
$var wire 32 , instr_data [31:0] $end
$var wire 32 - pc_debug [31:0] $end
$var wire 1 . reg_write $end
$var wire 1 * rst_n $end
$var wire 1 / use_imm $end
$var wire 32 0 write_data [31:0] $end
$var wire 32 1 rs2_data [31:0] $end
$var wire 5 2 rs2 [4:0] $end
$var wire 32 3 rs1_data [31:0] $end
$var wire 5 4 rs1 [4:0] $end
$var wire 5 5 rd [4:0] $end
$var wire 7 6 opcode [6:0] $end
$var wire 1 7 is_op_imm $end
$var wire 1 8 is_op $end
$var wire 1 9 is_lui $end
$var wire 32 : imm_u [31:0] $end
$var wire 32 ; imm_i [31:0] $end
$var wire 7 < funct7 [6:0] $end
$var wire 3 = funct3 [2:0] $end
$var wire 32 > alu_result [31:0] $end
$var parameter 4 ? ALU_ADD $end
$var parameter 4 @ ALU_AND $end
$var parameter 4 A ALU_OR $end
$var parameter 4 B ALU_SUB $end
$var parameter 4 C ALU_XOR $end
$var reg 32 D alu_a [31:0] $end
$var reg 32 E alu_b [31:0] $end
$var reg 4 F alu_op [3:0] $end
$var reg 32 G data_addr [31:0] $end
$var reg 1 % data_re $end
$var reg 32 H data_wdata [31:0] $end
$var reg 1 # data_we $end
$var reg 32 I instr_addr [31:0] $end
$var reg 32 J pc [31:0] $end
$var integer 32 K i [31:0] $end
$upscope $end
$upscope $end
$enddefinitions $end
$comment Show the parameter values. $end
$dumpall
b100 C
b1 B
b11 A
b10 @
b0 ?
$end
#0
$dumpvars
b100000 K
b10000000000000000000000000000000 J
b10000000000000000000000000000000 I
bx H
bx G
bx F
bx E
bx D
bx >
bx =
bx <
bx ;
bx000000000000 :
x9
x8
x7
bx 6
bx 5
bx 4
bx 3
bx 2
bx 1
bx 0
x/
x.
b10000000000000000000000000000000 -
bx ,
bx +
0*
bx )
bx (
0'
bx &
x%
bx $
x#
b10000000000000000000000000000000 "
b10000000000000000000000000000000 !
$end
#5000
b100000 K
1'
#10000
0'
#15000
b100000 K
1'
#20000
0'
1*
#25000
b10000000000000000000000000000100 "
b10000000000000000000000000000100 I
b10000000000000000000000000000100 !
b10000000000000000000000000000100 -
b10000000000000000000000000000100 J
b101 0
b101 &
b101 G
b101 >
1.
0%
0#
b0 $
b0 H
b0 D
1/
b0 3
b0 1
b0 F
b101 E
17
08
09
b10011 6
b1 5
b0 =
b0 4
b101 2
b0 <
b101 ;
b10100000000000000000000 :
b10100000000000010010011 )
b10100000000000010010011 ,
1'
#30000
0'
#35000
b101 D
b101 3
b10000000000000000000000000001000 "
b10000000000000000000000000001000 I
b10000000000000000000000000001000 !
b10000000000000000000000000001000 -
b10000000000000000000000000001000 J
b1000 0
b1000 &
b1000 G
b1000 >
b11 E
b10 5
b1 4
b11 2
b11 ;
b1100001000000000000000 :
b1100001000000100010011 )
b1100001000000100010011 ,
1'
#40000
0'
#45000
b1000 $
b1000 H
b1000 1
b10000000000000000000000000001100 "
b10000000000000000000000000001100 I
b10000000000000000000000000001100 !
b10000000000000000000000000001100 -
b10000000000000000000000000001100 J
b1101 0
b1101 &
b1101 G
b1101 >
0/
b1000 E
07
18
b110011 6
b11 5
b10 2
b10 ;
b1000001000000000000000 :
b1000001000000110110011 )
b1000001000000110110011 ,
1'
#50000
0'
#55000
b10000000000000000000000000010000 "
b10000000000000000000000000010000 I
b10000000000000000000000000010000 !
b10000000000000000000000000010000 -
b10000000000000000000000000010000 J
1'
#60000
0'
#65000
b10000000000000000000000000010100 "
b10000000000000000000000000010100 I
b10000000000000000000000000010100 !
b10000000000000000000000000010100 -
b10000000000000000000000000010100 J
1'
#70000
0'
#75000
b10000000000000000000000000011000 "
b10000000000000000000000000011000 I
b10000000000000000000000000011000 !
b10000000000000000000000000011000 -
b10000000000000000000000000011000 J
1'
#80000
0'
#85000
b10000000000000000000000000011100 "
b10000000000000000000000000011100 I
b10000000000000000000000000011100 !
b10000000000000000000000000011100 -
b10000000000000000000000000011100 J
1'
#90000
0'
#95000
b10000000000000000000000000100000 "
b10000000000000000000000000100000 I
b10000000000000000000000000100000 !
b10000000000000000000000000100000 -
b10000000000000000000000000100000 J
1'
#100000
0'
#105000
b10000000000000000000000000100100 "
b10000000000000000000000000100100 I
b10000000000000000000000000100100 !
b10000000000000000000000000100100 -
b10000000000000000000000000100100 J
1'
#110000
0'
#115000
b10000000000000000000000000101000 "
b10000000000000000000000000101000 I
b10000000000000000000000000101000 !
b10000000000000000000000000101000 -
b10000000000000000000000000101000 J
1'
#120000
0'
#125000
b10000000000000000000000000101100 "
b10000000000000000000000000101100 I
b10000000000000000000000000101100 !
b10000000000000000000000000101100 -
b10000000000000000000000000101100 J
1'
#130000
0'
#135000
b10000000000000000000000000110000 "
b10000000000000000000000000110000 I
b10000000000000000000000000110000 !
b10000000000000000000000000110000 -
b10000000000000000000000000110000 J
1'
#140000
0'
#145000
b10000000000000000000000000110100 "
b10000000000000000000000000110100 I
b10000000000000000000000000110100 !
b10000000000000000000000000110100 -
b10000000000000000000000000110100 J
1'
